siiau_consultas_api/__init__.py
siiau_consultas_api/__main__.py
siiau_consultas_api/cli.py
siiau_consultas_api/colores.py
siiau_consultas_api/consulta_cli.py
siiau_consultas_api/consulta_tui.py
siiau_consultas_api/esquemas.py
siiau_consultas_api/getch.py
siiau_consultas_api/posibles_horarios.py
siiau_consultas_api/servicio_consulta_siiau.py
siiau_consultas_api/servicio_consultar.py
siiau_consultas_api/servicio_horario_siiau.py
siiau_consultas_api/servicio_oferta_siiau.py
siiau_consultas_api/servicio_registro.py
siiau_consultas_api/servicio_tabla.py
siiau_consultas_api/utiles.py
siiau_consultas_api/__pycache__/__init__.cpython-38.pyc
siiau_consultas_api/__pycache__/colores.cpython-38.pyc
siiau_consultas_api/__pycache__/consulta_cli.cpython-38.pyc
siiau_consultas_api/__pycache__/esquemas.cpython-38.pyc
siiau_consultas_api/__pycache__/getch.cpython-38.pyc
siiau_consultas_api/__pycache__/servicio_consulta_siiau.cpython-38.pyc
siiau_consultas_api/__pycache__/utiles.cpython-38.pyc
siiau_consultas_api-0.0.2.dist-info/LICENSE
siiau_consultas_api-0.0.2.dist-info/LICENSE.txt
siiau_consultas_api-0.0.2.dist-info/METADATA
siiau_consultas_api-0.0.2.dist-info/WHEEL
siiau_consultas_api-0.0.2.dist-info/entry_points.txt
siiau_consultas_api-0.0.2.dist-info/top_level.txt
siiau_consultas_api-0.0.2.dist-info/RECORD
